choosem/__init__.py
choosem/cli/__init__.py
choosem/cli/focus.py
choosem/cli/insert.py
choosem/cli/launch.py
choosem/data/adlam.csv
choosem/data/aegean_numbers.csv
choosem/data/ahom.csv
choosem/data/alchemical_symbols.csv
choosem/data/alphabetic_presentation_forms.csv
choosem/data/anatolian_hieroglyphs.csv
choosem/data/ancient_greek_musical_notation.csv
choosem/data/ancient_greek_numbers.csv
choosem/data/ancient_symbols.csv
choosem/data/arabic.csv
choosem/data/arabic_extended-a.csv
choosem/data/arabic_mathematical_alphabetic_symbols.csv
choosem/data/arabic_presentation_forms-a.csv
choosem/data/arabic_presentation_forms-b.csv
choosem/data/arabic_supplement.csv
choosem/data/armenian.csv
choosem/data/arrows.csv
choosem/data/avestan.csv
choosem/data/balinese.csv
choosem/data/bamum.csv
choosem/data/bamum_supplement.csv
choosem/data/basic_latin.csv
choosem/data/bassa_vah.csv
choosem/data/batak.csv
choosem/data/bengali.csv
choosem/data/bhaiksuki.csv
choosem/data/block_elements.csv
choosem/data/bopomofo.csv
choosem/data/bopomofo_extended.csv
choosem/data/box_drawing.csv
choosem/data/brahmi.csv
choosem/data/braille_patterns.csv
choosem/data/buginese.csv
choosem/data/buhid.csv
choosem/data/byzantine_musical_symbols.csv
choosem/data/carian.csv
choosem/data/caucasian_albanian.csv
choosem/data/chakma.csv
choosem/data/cham.csv
choosem/data/cherokee.csv
choosem/data/cherokee_supplement.csv
choosem/data/chess_symbols.csv
choosem/data/cjk_compatibility.csv
choosem/data/cjk_compatibility_forms.csv
choosem/data/cjk_compatibility_ideographs.csv
choosem/data/cjk_compatibility_ideographs_supplement.csv
choosem/data/cjk_radicals_supplement.csv
choosem/data/cjk_strokes.csv
choosem/data/cjk_symbols_and_punctuation.csv
choosem/data/combining_diacritical_marks.csv
choosem/data/combining_diacritical_marks_extended.csv
choosem/data/combining_diacritical_marks_for_symbols.csv
choosem/data/combining_diacritical_marks_supplement.csv
choosem/data/combining_half_marks.csv
choosem-0.1.0.dist-info/entry_points.txt
choosem-0.1.0.dist-info/WHEEL
choosem-0.1.0.dist-info/METADATA
choosem-0.1.0.dist-info/RECORD
