Metadata-Version: 2.1
Name: choosem
Version: 0.1.0
Summary: dropdown picker/launcher for macos
Home-page: https://github.com/Granitosaurus/choosem
License: GPL-3.0-or-later
Keywords: macos,chooser,picker,launcher
Author: Bernardas Alisauskas
Author-email: bernardas.alisauskas@pm.me
Requires-Python: >=3.6,<4.0
Classifier: Development Status :: 4 - Beta
Classifier: License :: OSI Approved :: GNU General Public License v3 or later (GPLv3+)
Classifier: Programming Language :: Python :: 3
Classifier: Programming Language :: Python :: 3.6
Classifier: Programming Language :: Python :: 3.7
Classifier: Programming Language :: Python :: 3.8
Classifier: Topic :: Utilities
Requires-Dist: click (>=7.1.2,<8.0.0)
Project-URL: Repository, https://github.com/Granitosaurus/choosem
